<?xml version="1.0" encoding="utf-8" ?>
<dwsync>
<file name="build-config.js" server="irapture.com//webapps/" local="130216614710000000" remote="130368924000000000" Dst="0" />
<file name="CHANGES.md" server="irapture.com//webapps/" local="130216614710000000" remote="130368924000000000" Dst="0" />
<file name="config.js" server="irapture.com//webapps/" local="130535545532905709" remote="130535545200000000" Dst="0" />
<file name="contents.css" server="irapture.com//webapps/" local="130216614710000000" remote="130368924000000000" Dst="0" />
<file name="ckeditor.js" server="irapture.com//webapps/" local="130216614710000000" remote="130368924000000000" Dst="0" />
<file name="LICENSE.md" server="irapture.com//webapps/" local="130216614710000000" remote="130368924000000000" Dst="0" />
<file name="README.md" server="irapture.com//webapps/" local="130216614710000000" remote="130368925800000000" Dst="0" />
<file name="styles.js" server="irapture.com//webapps/" local="130216614710000000" remote="130368926400000000" Dst="0" />
</dwsync>